LICENSE
MANIFEST.in
README.rst
setup.py
btc_flex_forms.egg-info/PKG-INFO
btc_flex_forms.egg-info/SOURCES.txt
btc_flex_forms.egg-info/dependency_links.txt
btc_flex_forms.egg-info/requires.txt
btc_flex_forms.egg-info/top_level.txt
flex_forms/__init__.py
flex_forms/apps.py
flex_forms/components.py
flex_forms/examples.py
flex_forms/forms.py
flex_forms/utils.py
flex_forms/static/flex_forms/css/default.css
flex_forms/static/flex_forms/img/expand_more-24px.svg
flex_forms/templates/flex_forms/blocks/block.html
flex_forms/templates/flex_forms/blocks/row.html
flex_forms/templates/flex_forms/fields/checkbox.html
flex_forms/templates/flex_forms/fields/checkbox_multi.html
flex_forms/templates/flex_forms/fields/data_array.html
flex_forms/templates/flex_forms/fields/generic.html
flex_forms/templates/flex_forms/fields/plain.html
flex_forms/templates/flex_forms/fields/radio.html
flex_forms/templates/flex_forms/fields/static.html
flex_forms/templates/flex_forms/fields/static_button.html
flex_forms/templates/flex_forms/fieldsets/generic_fieldset.html
flex_forms/templates/flex_forms/forms/base_template.html
flex_forms/templates/flex_forms/forms/generic_form.html
flex_forms/templates/flex_forms/forms/generic_form_body.html
flex_forms/templates/flex_forms/forms/generic_formset.html
flex_forms/templates/flex_forms/forms/generic_formset_body.html
flex_forms/templates/flex_forms/forms/group_template.html
flex_forms/templatetags/__init__.py
flex_forms/templatetags/flex_forms.py